{
  "timestamp": "2026-02-27T19:42:37",
  "delta_mode": 0,
  "stages": {
    "triple_extraction": {
      "input_tokens": 9811,
      "output_tokens": 2945,
      "total_tokens": 12756,
      "calls": [
        {
          "node": "summarize_chunk",
          "input_tokens": 273,
          "output_tokens": 96,
          "total_tokens": 369
        },
        {
          "node": "summarize_chunk",
          "input_tokens": 371,
          "output_tokens": 93,
          "total_tokens": 464
        },
        {
          "node": "summarize_chunk",
          "input_tokens": 359,
          "output_tokens": 107,
          "total_tokens": 466
        },
        {
          "node": "summarize_chunk",
          "input_tokens": 347,
          "output_tokens": 103,
          "total_tokens": 450
        },
        {
          "node": "summarize_chunk",
          "input_tokens": 319,
          "output_tokens": 110,
          "total_tokens": 429
        },
        {
          "node": "summarize_chunk",
          "input_tokens": 364,
          "output_tokens": 96,
          "total_tokens": 460
        },
        {
          "node": "summarize_chunk",
          "input_tokens": 347,
          "output_tokens": 108,
          "total_tokens": 455
        },
        {
          "node": "summarize_chunk",
          "input_tokens": 327,
          "output_tokens": 104,
          "total_tokens": 431
        },
        {
          "node": "summarize_chunk",
          "input_tokens": 302,
          "output_tokens": 109,
          "total_tokens": 411
        },
        {
          "node": "summarize_chunk",
          "input_tokens": 353,
          "output_tokens": 91,
          "total_tokens": 444
        },
        {
          "node": "summarize_chunk",
          "input_tokens": 343,
          "output_tokens": 119,
          "total_tokens": 462
        },
        {
          "node": "summarize_chunk",
          "input_tokens": 330,
          "output_tokens": 112,
          "total_tokens": 442
        },
        {
          "node": "summarize_chunk",
          "input_tokens": 315,
          "output_tokens": 110,
          "total_tokens": 425
        },
        {
          "node": "summarize_chunk",
          "input_tokens": 361,
          "output_tokens": 112,
          "total_tokens": 473
        },
        {
          "node": "summarize_chunk",
          "input_tokens": 366,
          "output_tokens": 105,
          "total_tokens": 471
        },
        {
          "node": "summarize_chunk",
          "input_tokens": 341,
          "output_tokens": 84,
          "total_tokens": 425
        },
        {
          "node": "summarize_chunk",
          "input_tokens": 315,
          "output_tokens": 106,
          "total_tokens": 421
        },
        {
          "node": "summarize_chunk",
          "input_tokens": 347,
          "output_tokens": 88,
          "total_tokens": 435
        },
        {
          "node": "summarize_chunk",
          "input_tokens": 350,
          "output_tokens": 98,
          "total_tokens": 448
        },
        {
          "node": "summarize_chunk",
          "input_tokens": 340,
          "output_tokens": 111,
          "total_tokens": 451
        },
        {
          "node": "summarize_chunk",
          "input_tokens": 374,
          "output_tokens": 105,
          "total_tokens": 479
        },
        {
          "node": "summarize_chunk",
          "input_tokens": 334,
          "output_tokens": 108,
          "total_tokens": 442
        },
        {
          "node": "summarize_chunk",
          "input_tokens": 364,
          "output_tokens": 100,
          "total_tokens": 464
        },
        {
          "node": "summarize_chunk",
          "input_tokens": 315,
          "output_tokens": 84,
          "total_tokens": 399
        },
        {
          "node": "summarize_chunk",
          "input_tokens": 315,
          "output_tokens": 94,
          "total_tokens": 409
        },
        {
          "node": "summarize_chunk",
          "input_tokens": 314,
          "output_tokens": 88,
          "total_tokens": 402
        },
        {
          "node": "summarize_chunk",
          "input_tokens": 377,
          "output_tokens": 98,
          "total_tokens": 475
        },
        {
          "node": "summarize_chunk",
          "input_tokens": 327,
          "output_tokens": 92,
          "total_tokens": 419
        },
        {
          "node": "summarize_chunk",
          "input_tokens": 321,
          "output_tokens": 114,
          "total_tokens": 435
        }
      ]
    },
    "context_generation": {
      "input_tokens": 6934,
      "output_tokens": 231,
      "total_tokens": 7165,
      "calls": [
        {
          "node": "iot_decide",
          "input_tokens": 924,
          "output_tokens": 90,
          "total_tokens": 1014
        },
        {
          "node": "iot_react",
          "input_tokens": 2978,
          "output_tokens": 132,
          "total_tokens": 3110
        },
        {
          "node": "iot_react",
          "input_tokens": 3032,
          "output_tokens": 9,
          "total_tokens": 3041
        }
      ]
    },
    "triple_refinement": {
      "input_tokens": 3073,
      "output_tokens": 38,
      "total_tokens": 3111,
      "calls": [
        {
          "node": "validation_decide",
          "input_tokens": 3073,
          "output_tokens": 38,
          "total_tokens": 3111
        }
      ]
    }
  }
}